Week8/q1/q1.v
module q1(a, b, c, en, y);
input en, a, b, c;
output [7:0]y;
wire [1:0]e;
assign e[0] = en & ~a;
assign e[1] = en & a;
dec2to4 stage0(b, c, e[0], y[3:0]);
dec2to4 stage1(b, c, e[1], y[7:4]);
endmodule

module dec2to4(a, b, en, y);
   input en,a,b;
   output reg [3:0] y;
   always @(en or a or b)
     begin
       if(en==1'b1)
         begin
           if(a==1'b0 && b==1'b0) 
           	y=4'b0001;
           else if(a==1'b0 && b==1'b1) 
           	y=4'b0010;
           else if(a==1'b1 && b==1'b0) 
           	y=4'b0100;
           else if(a==1'b1 && b==1'b1) 
           	y=4'b1000;
         end
       else
        y=4'b0000;
     end
endmodule

Week8/q1/q1_tb.v
`timescale 1ns/1ns
`include "q1.v"
module q1_tb();
reg a,b,c,en;
wire [7:0]y;
q1 qn1(a, b, c, en, y);
initial
begin
      //$monitor("en=%b a=%b b=%b y=%b",en,a,b,y);
      $dumpfile("q1_tb.vcd");
      $dumpvars(0, q1_tb);
      //en=0;a=1'bx;b=1'bx; c=1'bx;
      //#20;
      en=1;a=0;b=0; c=0;
      #20;
      en=1;a=0;b=0; c=1;
      #20;
      en=1;a=0;b=1; c=0;
      #20;
      en=1;a=0;b=1; c=1;
      #20;
      en=1;a=1;b=0; c=0;
      #20;
      en=1;a=1;b=0; c=1;
      #20;
      en=1;a=1;b=1; c=0;
      #20;
      en=1;a=1;b=1; c=1;
      #20;
      $display("test complete");
end
endmodule

Week8/q1/q1_tb.vcd
$date
	Mon Oct 17 16:08:00 2022
$end
$version
	Icarus Verilog
$end
$timescale
	1ns
$end
$scope module q1_tb $end
$var wire 8 ! y [7:0] $end
$var reg 1 " a $end
$var reg 1 # b $end
$var reg 1 $ c $end
$var reg 1 % en $end
$scope module qn1 $end
$var wire 1 " a $end
$var wire 1 # b $end
$var wire 1 $ c $end
$var wire 1 % en $end
$var wire 8 & y [7:0] $end
$var wire 2 ' e [1:0] $end
$scope module stage0 $end
$var wire 1 # a $end
$var wire 1 $ b $end
$var wire 1 ( en $end
$var reg 4 ) y [3:0] $end
$upscope $end
$scope module stage1 $end
$var wire 1 # a $end
$var wire 1 $ b $end
$var wire 1 * en $end
$var reg 4 + y [3:0] $end
$upscope $end
$upscope $end
$upscope $end
$enddefinitions $end
#0
$dumpvars
b0 +
0*
b1 )
1(
b1 '
b1 &
1%
0$
0#
0"
b1 !
$end
#20
b10 !
b10 &
b10 )
1$
#40
b100 !
b100 &
b100 )
0$
1#
#60
b1000 !
b1000 &
b1000 )
1$
#80
0(
b1 +
1*
b10000 !
b10000 &
b0 )
b10 '
0$
0#
1"
#100
b100000 !
b100000 &
b10 +
1$
#120
b1000000 !
b1000000 &
b100 +
0$
1#
#140
b10000000 !
b10000000 &
b1000 +
1$
