prog_1.v
module prog_1(a,b,c,d,f);
input a,b,c,d;
output f;
and(k1,a,b);
or(k2,k1,c);
not(k3,k2);
and (k4,k3,d);

and(l1,a,b);
or(l2,l1,c);
or(l3,l2,d);

and(f,k4,l3);
endmodule

week1/prog_1_tb.v
`timescale 1ns/1ns
`include "prog_1.v"
module prog_1_tb;

reg a,b,c,d;
wire f;

prog_1 uut(a,b,c,d,f);
initial begin

	$dumpfile("prog_1_tb.vcd");
	$dumpvars(0,prog_1_tb);
	
	a=0;b=0;c=0;d=0;#20;
	
	a=0;b=0;c=0;d=1;#20;
	
	a=0;b=0;c=1;d=0;#20;
	
	a=0;b=0;c=1;d=1;#20;
	
	a=0;b=1;c=0;d=0;#20;
	
	a=0;b=1;c=0;d=1;#20;
	
	a=0;b=1;c=1;d=0;#20;
	
	a=0;b=1;c=1;d=1;#20;
	
	a=1;b=0;c=0;d=0;#20;
	
	a=1;b=0;c=0;d=1;#20;
	
	a=1;b=0;c=1;d=0;#20;
	
	a=1;b=0;c=1;d=1;#20;
	
	a=1;b=1;c=0;d=0;#20;
	
	a=1;b=1;c=0;d=1;#20;
	
	a=1;b=1;c=1;d=0;#20;
	
	a=1;b=1;c=1;d=1;#20;


$display("Test Complete");
end
endmodule

prog_1_tb.vcd
$date
	Mon Aug 22 15:16:19 2022
$end
$version
	Icarus Verilog
$end
$timescale
	1ns
$end
$scope module prog_1_tb $end
$var wire 1 ! f $end
$var reg 1 " a $end
$var reg 1 # b $end
$var reg 1 $ c $end
$var reg 1 % d $end
$scope module uut $end
$var wire 1 " a $end
$var wire 1 # b $end
$var wire 1 $ c $end
$var wire 1 % d $end
$var wire 1 ! f $end
$var wire 1 & k1 $end
$var wire 1 ' k2 $end
$var wire 1 ( k3 $end
$var wire 1 ) k4 $end
$var wire 1 * l1 $end
$var wire 1 + l2 $end
$var wire 1 , l3 $end
$upscope $end
$upscope $end
$enddefinitions $end
#0
$dumpvars
0,
0+
0*
0)
1(
0'
0&
0%
0$
0#
0"
0!
$end
#20
1!
1)
1,
1%
#40
0!
0(
0)
1'
1+
0%
1$
#60
1%
#80
1(
0,
0'
0+
0%
0$
1#
#100
1!
1)
1,
1%
#120
0!
0(
0)
1'
1+
0%
1$
#140
1%
#160
1(
0,
0'
0+
0%
0$
0#
1"
#180
1!
1)
1,
1%
#200
0!
0(
0)
1'
1+
0%
1$
#220
1%
#240
1&
1*
0%
0$
1#
#260
1%
#280
0%
1$
#300
1%
