example.v
module example(x1, x2, x3, f);
input x1, x2, x3;
output f;
and (g, x1, x2);
not (k, x2);
and (h, k, x3);
or (f, g, h);
endmodule

example_tb.v
`timescale 1ns/1ns
`include "example.v"
//Name of the Verilog file
module example_tb();
reg x1, x2, x3;
//Input
wire f;
//Output
example ex2(x1, x2, x3, f); //Instantiation of the module
initial
begin
$dumpfile("example_tb.vcd");
$dumpvars(0, example_tb);
x1=1'b0; x2=1'b0; x3=1'b0;
#20;
x1=1'b0; x2=1'b0; x3=1'b1;
#20;
x1=1'b0; x2=1'b1; x3=1'b0;
#20;
x1=1'b0; x2=1'b1; x3=1'b1;
#20;
x1=1'b1; x2=1'b0; x3=1'b0;
#20;
x1=1'b1; x2=1'b0; x3=1'b1;
#20;
x1=1'b1; x2=1'b1; x3=1'b0;
#20;
x1=1'b1; x2=1'b1; x3=1'b1;
#20;
$display("Test complete");
end
endmodule

week1/example_tb.vcd
$date
	Mon Aug 22 14:33:29 2022
$end
$version
	Icarus Verilog
$end
$timescale
	1ns
$end
$scope module example_tb $end
$var wire 1 ! f $end
$var reg 1 " x1 $end
$var reg 1 # x2 $end
$var reg 1 $ x3 $end
$scope module ex2 $end
$var wire 1 ! f $end
$var wire 1 % g $end
$var wire 1 & h $end
$var wire 1 ' k $end
$var wire 1 " x1 $end
$var wire 1 # x2 $end
$var wire 1 $ x3 $end
$upscope $end
$upscope $end
$enddefinitions $end
#0
$dumpvars
1'
0&
0%
0$
0#
0"
0!
$end
#20
1!
1&
1$
#40
0!
0&
0'
0$
1#
#60
1$
#80
1'
0$
0#
1"
#100
1!
1&
1$
#120
0&
1%
0'
0$
1#
#140
1$
