week2/prog2_1.v
module prog2_1(a,b,c,d,f);
input a,b,c,d;
output f;
assign f = (b|c)&(~b|d);
endmodule

Untitled_Message/prog2_1_tb.v
`timescale 1ns/1ns
`include "prog2_1.v"
module prog2_1_tb();

reg a,b,c,d;
wire f;

prog2_1 uut(a,b,c,d,f);
initial begin

	$dumpfile("prog2_1_tb.vcd");
	$dumpvars(0,prog2_1_tb);
	
	a=0;b=0;c=0;d=0;#20;
	
	a=0;b=0;c=0;d=1;#20;
	
	a=0;b=0;c=1;d=0;#20;
	
	a=0;b=0;c=1;d=1;#20;
	
	a=0;b=1;c=0;d=0;#20;
	
	a=0;b=1;c=0;d=1;#20;
	
	a=0;b=1;c=1;d=0;#20;
	
	a=0;b=1;c=1;d=1;#20;
	
	a=1;b=0;c=0;d=0;#20;
	
	a=1;b=0;c=0;d=1;#20;
	
	a=1;b=0;c=1;d=0;#20;
	
	a=1;b=0;c=1;d=1;#20;
	
	a=1;b=1;c=0;d=0;#20;
	
	a=1;b=1;c=0;d=1;#20;
	
	a=1;b=1;c=1;d=0;#20;
	
	a=1;b=1;c=1;d=1;#20;


$display("Test Complete");
end
endmodule

week2/prog2_1_tb.vcd
$date
	Mon Aug 29 16:15:10 2022
$end
$version
	Icarus Verilog
$end
$timescale
	1ns
$end
$scope module prog2_1_tb $end
$var wire 1 ! f $end
$var reg 1 " a $end
$var reg 1 # b $end
$var reg 1 $ c $end
$var reg 1 % d $end
$scope module uut $end
$var wire 1 " a $end
$var wire 1 # b $end
$var wire 1 $ c $end
$var wire 1 % d $end
$var wire 1 ! f $end
$upscope $end
$upscope $end
$enddefinitions $end
#0
$dumpvars
0%
0$
0#
0"
0!
$end
#20
1%
#40
1!
0%
1$
#60
1%
#80
0!
0%
0$
1#
#100
1!
1%
#120
0!
0%
1$
#140
1!
1%
#160
0!
0%
0$
0#
1"
#180
1%
#200
1!
0%
1$
#220
1%
#240
0!
0%
0$
1#
#260
1!
1%
#280
0!
0%
1$
#300
1!
1%
