Untitled_Message/prog1_2.v
module prog1_2(a,b,c,d,f);
input a,b,c,d;
output f;
assign f = (b&~c&~d)|(~b&c)|(~b&d);
endmodule

week2/prog1_2_tb.v
`timescale 1ns/1ns
`include "prog1_2.v"
module prog1_2_tb();

reg a,b,c,d;
wire f;

prog1_2 uut(a,b,c,d,f);
initial begin

	$dumpfile("prog1_2_tb.vcd");
	$dumpvars(0,prog1_2_tb);
	
	a=0;b=0;c=0;d=0;#20;
	
	a=0;b=0;c=0;d=1;#20;
	
	a=0;b=0;c=1;d=0;#20;
	
	a=0;b=0;c=1;d=1;#20;
	
	a=0;b=1;c=0;d=0;#20;
	
	a=0;b=1;c=0;d=1;#20;
	
	a=0;b=1;c=1;d=0;#20;
	
	a=0;b=1;c=1;d=1;#20;
	
	a=1;b=0;c=0;d=0;#20;
	
	a=1;b=0;c=0;d=1;#20;
	
	a=1;b=0;c=1;d=0;#20;
	
	a=1;b=0;c=1;d=1;#20;
	
	a=1;b=1;c=0;d=0;#20;
	
	a=1;b=1;c=0;d=1;#20;
	
	a=1;b=1;c=1;d=0;#20;
	
	a=1;b=1;c=1;d=1;#20;


$display("Test Complete");
end
endmodule

Untitled_Message/prog1_2_tb.vcd
$date
	Mon Aug 29 15:52:57 2022
$end
$version
	Icarus Verilog
$end
$timescale
	1ns
$end
$scope module prog1_2_tb $end
$var wire 1 ! f $end
$var reg 1 " a $end
$var reg 1 # b $end
$var reg 1 $ c $end
$var reg 1 % d $end
$scope module uut $end
$var wire 1 " a $end
$var wire 1 # b $end
$var wire 1 $ c $end
$var wire 1 % d $end
$var wire 1 ! f $end
$upscope $end
$upscope $end
$enddefinitions $end
#0
$dumpvars
0%
0$
0#
0"
0!
$end
#20
1!
1%
#40
0%
1$
#60
1%
#80
1!
0%
0$
1#
#100
0!
1%
#120
0%
1$
#140
1%
#160
0%
0$
0#
1"
#180
1!
1%
#200
0%
1$
#220
1%
#240
1!
0%
0$
1#
#260
0!
1%
#280
0%
1$
#300
1%
