week3/prog1.v
module prog1(a,b,c,d,f);
input a,b,c,d;
output f;
assign f = ~&((a~&(b~&b))~&(c~&(d~&d)));
endmodule

week3/prog1_tb.v
`timescale 1ns/1ns
`include "prog1.v"
module prog1_tb();

reg a,b,c,d;
wire f;

prog1 uut(a,b,c,d,f);
initial begin

	$dumpfile("prog1_tb.vcd");
	$dumpvars(0,prog1_tb);
	
	a=0;b=0;c=0;d=0;#20;
	
	a=0;b=0;c=0;d=1;#20;
	
	a=0;b=0;c=1;d=0;#20;
	
	a=0;b=0;c=1;d=1;#20;
	
	a=0;b=1;c=0;d=0;#20;
	
	a=0;b=1;c=0;d=1;#20;
	
	a=0;b=1;c=1;d=0;#20;
	
	a=0;b=1;c=1;d=1;#20;
	
	a=1;b=0;c=0;d=0;#20;
	
	a=1;b=0;c=0;d=1;#20;
	
	a=1;b=0;c=1;d=0;#20;
	
	a=1;b=0;c=1;d=1;#20;
	
	a=1;b=1;c=0;d=0;#20;
	
	a=1;b=1;c=0;d=1;#20;
	
	a=1;b=1;c=1;d=0;#20;
	
	a=1;b=1;c=1;d=1;#20;


$display("Test Complete");
end
endmodule

week3/prog1_tb.vcd
$date
	Mon Sep  5 16:23:20 2022
$end
$version
	Icarus Verilog
$end
$timescale
	1ns
$end
$scope module prog1_tb $end
$var wire 1 ! f $end
$var reg 1 " a $end
$var reg 1 # b $end
$var reg 1 $ c $end
$var reg 1 % d $end
$scope module uut $end
$var wire 1 " a $end
$var wire 1 # b $end
$var wire 1 $ c $end
$var wire 1 % d $end
$var wire 1 ! f $end
$upscope $end
$upscope $end
$enddefinitions $end
#0
$dumpvars
0%
0$
0#
0"
1!
$end
#20
1%
#40
0!
0%
1$
#60
1!
1%
#80
0%
0$
1#
#100
1%
#120
0!
0%
1$
#140
1!
1%
#160
0!
0%
0$
0#
1"
#180
1%
#200
0%
1$
#220
1%
#240
1!
0%
0$
1#
#260
1%
#280
0!
0%
1$
#300
1!
1%
